MANIFEST.in
setup.cfg
setup.py
autoreload/__init__.py
autoreload/admin.py
autoreload/apps.py
autoreload/conf.py
autoreload/models.py
autoreload/tests.py
autoreload/views.py
autoreload/management/__init__.py
autoreload/management/commands/__init__.py
autoreload/management/commands/autoreload.py
autoreload/migrations/__init__.py
autoreload/templates/autoreload/client.js
autoreload/templatetags/__init__.py
autoreload/templatetags/autoreload_tags.py
django_autoreload.egg-info/PKG-INFO
django_autoreload.egg-info/SOURCES.txt
django_autoreload.egg-info/dependency_links.txt
django_autoreload.egg-info/not-zip-safe
django_autoreload.egg-info/requires.txt
django_autoreload.egg-info/top_level.txt