Metadata-Version: 1.1
Name: django-autoreload
Version: 0.1.1
Summary: Autoreload files in browser for Django development
Home-page: https://github.com/synw/django-autoreload
Author: synw
Author-email: synwe@yahoo.com
License: UNKNOWN
Download-URL: https://github.com/synw/django-autoreload/releases/tag/0.1.1
Keywords: django,development
Platform: UNKNOWN
Classifier: Development Status :: 3 - Alpha
Classifier: Framework :: Django :: 1.11
Classifier: Intended Audience :: Developers
Classifier: License :: OSI Approved :: MIT License
Classifier: Programming Language :: Python :: 3.5
